mongo_system_log/__init__.py
mongo_system_log/mongodb_connector.py
mongo_system_log/system_log.py
mongo_system_log-0.1.6.dist-info/LICENSE.txt
mongo_system_log-0.1.6.dist-info/METADATA
mongo_system_log-0.1.6.dist-info/WHEEL
mongo_system_log-0.1.6.dist-info/top_level.txt
mongo_system_log-0.1.6.dist-info/RECORD
