Metadata-Version: 2.1
Name: mongo-system-log
Version: 0.1.6
Summary: A log package that works with MongoDB.
Home-page: https://github.com/ronaldodduarte/mongo_system_log
Author: Ronaldo Duarte
Author-email: ronaldoduarte@globo.com
License: GNU
Classifier: Programming Language :: Python :: 3
Classifier: License :: OSI Approved :: GNU Lesser General Public License v3 (LGPLv3)
Classifier: Operating System :: OS Independent
Requires-Python: >=3.6
License-File: LICENSE.txt
Requires-Dist: pymongo ==4.7.3
